tokko_locations_client/__init__.py
tokko_locations_client/core.py
tokko_locations_client/exceptions.py
tokko_locations_client/helpers.py
tokko_locations_client/models.py
tokko_locations_client/tests.py
tokko_locations_client-0.0.3.dist-info/METADATA
tokko_locations_client-0.0.3.dist-info/WHEEL
tokko_locations_client-0.0.3.dist-info/top_level.txt
tokko_locations_client-0.0.3.dist-info/RECORD
