Metadata-Version: 2.1
Name: tokko-locations-client
Version: 0.0.3
Summary: Tokko Locations API Client.
Home-page: https://github.com/TokkoLabs/services-tokkobroker/libraries/
Author: Jose Salgado
Author-email: jsalgado@navent.com
License: BSD License
Platform: UNKNOWN
Classifier: Environment :: Web Environment
Classifier: Intended Audience :: Developers
Classifier: License :: OSI Approved :: BSD License
Classifier: Operating System :: OS Independent
Classifier: Programming Language :: Python
Classifier: Programming Language :: Python :: 3.8
Classifier: Topic :: Internet :: WWW/HTTP
Classifier: Topic :: Internet :: WWW/HTTP :: Dynamic Content
Requires-Dist: requests (==2.24.0)
Requires-Dist: json-rpc (==1.13.0)
Requires-Dist: arrow (==0.17.0)
